translafast/__init__.py
translafast/core.py
translafast/languages.json
translafast-1.4.1.dist-info/LICENSE
translafast-1.4.1.dist-info/METADATA
translafast-1.4.1.dist-info/WHEEL
translafast-1.4.1.dist-info/top_level.txt
translafast-1.4.1.dist-info/RECORD
