Metadata-Version: 2.1
Name: translafast
Version: 1.4.1
Summary: A blazing-fast Python translation library with 178-language support and intelligent caching.
Home-page: https://translafast.xyz
Author: PozStudio
Author-email: support@translafast.xyz
Classifier: Programming Language :: Python :: 3
Classifier: License :: OSI Approved :: MIT License
Classifier: Operating System :: OS Independent
Requires-Python: >=3.6
License-File: LICENSE
Requires-Dist: googletrans ==4.0.0-rc1
